{
	"id":"002",
	"name":"Level 2",
	"rounds":
	[
		{"name":"1/5", "image":"fly.jpg", "words":["worm", "catapillar", "fly", "ant"], "answer":2},
		{"name":"2/5", "image":"acorns.jpg", "words":["rock", "acorn", "hat", "dragon"], "answer":1},
		{"name":"3/5", "image":"cherry.jpg", "words":["cherry", "apple", "plum", "peach"], "answer":0},
		{"name":"4/5", "image":"coffee.jpg", "words":["dirt", "egg", "rock", "coffee"], "answer":3},
		{"name":"5/5", "image":"surfer.jpg", "words":["surfer", "whale", "kite", "boat"], "answer":0}
	]
}